{
  "titolo_it": "Chi sono",
  "titolo_en": "About me",
  "testo_it": "Sono medico, ricercatore e docente universitario, con attività clinica e di ricerca in medicina della sessualità, andrologia ed endocrinologia. Insegno presso l'Università di Roma Tor Vergata.\n\nMi sono laureato nel 2010 presso l'Università di Roma Sapienza, dove ho ottenuto nel 2015 il titolo di specialista in Endocrinologia e nel 2019 il titolo di dottore di ricerca (PhD) in Scienze Endocrinologiche.\n\nHo frequentato per due semestri (agosto 2018 - febbraio 2019 e agosto 2019 - febbraio 2020) il Centro di Medicina della Riproduzione e Andrologia di Münster, in Germania, prima come parte del mio percorso di dottorato e poi come ricercatore post-doc.",
  "testo_en": "I am a physician, researcher and university professor, with clinical and research activity in sexual medicine, andrology and endocrinology. I teach at the University of Rome Tor Vergata.\n\n(Placeholder text — editable from the /admin panel)",
  "foto": ""
}
